gitreporter/__init__.py
gitreporter/__main__.py
gitreporter/commit.py
gitreporter/commit_statistic.py
gitreporter/config.py
gitreporter/diff.py
gitreporter/file.py
gitreporter/progressbar.py
gitreporter/report.py
gitreporter/repository.py
gitreporter/repository_statistic.py
gitreporter/statistic_values.py
gitreporter/textline.py
gitreporter/types.py
gitreporter/templates/report_template.mustache
gitreporter-0.2.13.dist-info/licenses/LICENSE
gitreporter-0.2.13.dist-info/METADATA
gitreporter-0.2.13.dist-info/WHEEL
gitreporter-0.2.13.dist-info/entry_points.txt
gitreporter-0.2.13.dist-info/top_level.txt
gitreporter-0.2.13.dist-info/RECORD
