Metadata-Version: 2.4
Name: gitreporter
Version: 0.2.13
Summary: Git Analysis Tool
Author-email: Michael Guttmann <michael.guttmann@live.at>
Project-URL: Homepage, https://github.com/Migutti/GitReporter
Classifier: Programming Language :: Python :: 3
Requires-Python: >=3.10
License-File: LICENSE
Requires-Dist: chevron>=0.14.0
Requires-Dist: gitdb>=4.0.11
Requires-Dist: GitPython>=3.1.41
Requires-Dist: Pygments>=2.17.2
Requires-Dist: smmap>=5.0.1
Dynamic: license-file
